aws_crllm/__init__.py
aws_crllm/crllm.py
aws_crllm/dataset.py
aws_crllm/modules/__init__.py
aws_crllm/modules/agent.py
aws_crllm/modules/base.py
aws_crllm/modules/chat.py
aws_crllm/modules/chunk.py
aws_crllm/modules/dataset.py
aws_crllm/modules/document.py
aws_crllm/modules/session.py
aws_crllm-0.1.0.dist-info/METADATA
aws_crllm-0.1.0.dist-info/WHEEL
aws_crllm-0.1.0.dist-info/RECORD
